[ {
  "timestamp" : 1773890420667,
  "agent" : "Agent-13",
  "source" : "ScienceDaily",
  "topic" : "Mecánica Cuántica",
  "x" : -4.0589213,
  "y" : 0.0,
  "z" : 31.96966,
  "confidence" : 0.9976149667279472,
  "context" : "BUILDING",
  "keywords" : [ "mecánica-cuántica", "jettra-learning", "sciencedaily" ]
}, {
  "timestamp" : 1773890445588,
  "agent" : "Jettra Wolf",
  "source" : "Disco Local",
  "topic" : "Arquitectura del Sistema Jettra",
  "x" : 14.470441,
  "y" : 0.0,
  "z" : 13.599286,
  "confidence" : 0.9910278675313109,
  "context" : "COMMANDING",
  "keywords" : [ "arquitectura-del-sistema-jettra", "jettra-learning", "disco local" ]
}, {
  "timestamp" : 1773888872738,
  "agent" : "Agent-11",
  "source" : "Google",
  "topic" : "Redes Neuronales",
  "x" : -0.692002,
  "y" : 0.0,
  "z" : 13.825344,
  "confidence" : 0.9908181309665308,
  "context" : "BUILDING",
  "keywords" : [ "redes-neuronales", "jettra-learning", "google" ]
} ]